data_hygiene-0.3.data/scripts/contactous.py
format/__init__.py
format/menu_borders.py
format/menu_margins.py
format/menu_padding.py
format/menu_style.py
data_hygiene-0.3.dist-info/LICENSE
data_hygiene-0.3.dist-info/METADATA
data_hygiene-0.3.dist-info/WHEEL
data_hygiene-0.3.dist-info/top_level.txt
data_hygiene-0.3.dist-info/RECORD
