Metadata-Version: 2.1
Name: data-hygiene
Version: 0.3
Summary: A menu driven package
Home-page: https://github.com/santosh051987/menulist
Author: Santosh Singh
Author-email: santosh@contactous.com
License: UNKNOWN
Platform: UNKNOWN
Classifier: Programming Language :: Python :: 3
Classifier: License :: OSI Approved :: MIT License
Classifier: Operating System :: OS Independent
